issuestracker/__init__.py
issuestracker/admin.py
issuestracker/apps.py
issuestracker/celery.py
issuestracker/conf.py
issuestracker/exceptions.py
issuestracker/signals.py
issuestracker/urls.py
issuestracker/management/__init__.py
issuestracker/management/commands/__init__.py
issuestracker/managers/__init__.py
issuestracker/managers/live.py
issuestracker/migrations/0001_initial.py
issuestracker/migrations/0002_auto_20190424_1640.py
issuestracker/migrations/0003_auto_20190429_1422.py
issuestracker/migrations/0004_auto_20190429_1423.py
issuestracker/migrations/0005_issue_dek.py
issuestracker/migrations/0006_auto_20190430_2144.py
issuestracker/migrations/0007_auto_20190430_2202.py
issuestracker/migrations/0008_remove_candidate_headshot.py
issuestracker/migrations/0009_auto_20190501_1852.py
issuestracker/migrations/0010_story_date_added.py
issuestracker/migrations/0011_auto_20190507_1607.py
issuestracker/migrations/0012_auto_20190614_1702.py
issuestracker/migrations/0013_auto_20190614_1841.py
issuestracker/migrations/0014_auto_20190701_1808.py
issuestracker/migrations/0015_auto_20190701_1852.py
issuestracker/migrations/__init__.py
issuestracker/models/Candidate.py
issuestracker/models/Category.py
issuestracker/models/Faq.py
issuestracker/models/Issue.py
issuestracker/models/Position.py
issuestracker/models/Story.py
issuestracker/models/Update.py
issuestracker/models/__init__.py
issuestracker/serializers/Candidate.py
issuestracker/serializers/Category.py
issuestracker/serializers/Faq.py
issuestracker/serializers/Issue.py
issuestracker/serializers/Position.py
issuestracker/serializers/Story.py
issuestracker/serializers/Update.py
issuestracker/serializers/__init__.py
issuestracker/serializers/bakery/CandidatePage.py
issuestracker/serializers/bakery/CategoryPage.py
issuestracker/serializers/bakery/HomePage.py
issuestracker/serializers/bakery/IssuePage.py
issuestracker/serializers/bakery/SiteMap.py
issuestracker/serializers/bakery/__init__.py
django_politico_issues_tracker-1.3.1.dist-info/LICENSE
django_politico_issues_tracker-1.3.1.dist-info/METADATA
django_politico_issues_tracker-1.3.1.dist-info/WHEEL
django_politico_issues_tracker-1.3.1.dist-info/top_level.txt
django_politico_issues_tracker-1.3.1.dist-info/RECORD
